LICENSE
MANIFEST.in
README.rst
pyproject.toml
setup.cfg
setup.py
django_transactional_task_queue/__init__.py
django_transactional_task_queue/admin.py
django_transactional_task_queue/apps.py
django_transactional_task_queue/celery.py
django_transactional_task_queue/models.py
django_transactional_task_queue/tests.py
django_transactional_task_queue.egg-info/PKG-INFO
django_transactional_task_queue.egg-info/SOURCES.txt
django_transactional_task_queue.egg-info/dependency_links.txt
django_transactional_task_queue.egg-info/requires.txt
django_transactional_task_queue.egg-info/top_level.txt
django_transactional_task_queue/management/__init__.py
django_transactional_task_queue/management/commands/__init__.py
django_transactional_task_queue/management/commands/django_transactional_task_queue.py
django_transactional_task_queue/migrations/0001_initial.py
django_transactional_task_queue/migrations/__init__.py