Metadata-Version: 2.1
Name: django-transactional-task-queue
Version: 0.1.2
Summary: A simple Celery-like transactional task queue for Django
Home-page: https://github.com/aivarsk/django-transactional-task-queue
Author: Aivars Kalvans
Author-email: aivars.kalvans@gmail.com
License: MIT
Classifier: Environment :: Web Environment
Classifier: Framework :: Django
Classifier: Framework :: Django :: 4.0
Classifier: Intended Audience :: Developers
Classifier: License :: OSI Approved :: MIT License
Classifier: Operating System :: OS Independent
Classifier: Programming Language :: Python
Classifier: Programming Language :: Python :: 3
Classifier: Programming Language :: Python :: 3 :: Only
Classifier: Programming Language :: Python :: 3.10
Classifier: Programming Language :: Python :: 3.11
Classifier: Programming Language :: Python :: 3.12
Requires-Python: >=3.10
License-File: LICENSE
Requires-Dist: Django>=4.0
